qucuQuantum/__init__.py
qucuQuantum/backend.py
qucuQuantum/cuCommand.py
qucuQuantum/cuQuantum.py
qucuQuantum/cuQuantumSim.py
qucuQuantum/exceptions.py
qucuQuantum/function_time.py
qucuQuantum/local_cuQuantum_python.py
qucuQuantum/result.py
quqcs-0.1.0.dist-info/WHEEL
quqcs-0.1.0.dist-info/METADATA
quqcs-0.1.0.dist-info/RECORD
