Metadata-Version: 2.1
Name: quqcs
Version: 0.1.0
Summary: quqcs is an open source library for quantum compute simulating on NVIDIA GPU
Home-page: http://www.qudoor.com/
License: Apache-2.0
Keywords: cuQuantum,quantum
Author: sunhaiyang
Author-email: sunhaiyang@qudoor.cn
Requires-Python: >=3.8,<3.11
Classifier: License :: OSI Approved :: Apache Software License
Classifier: Operating System :: MacOS
Classifier: Operating System :: Microsoft :: Windows
Classifier: Operating System :: POSIX :: Linux
Classifier: Programming Language :: Python :: 3
Classifier: Programming Language :: Python :: 3.8
Classifier: Programming Language :: Python :: 3.9
Classifier: Programming Language :: Python :: 3.10
Classifier: Programming Language :: Python :: 3.10
Classifier: Programming Language :: Python :: 3.8
Classifier: Programming Language :: Python :: 3.9
Classifier: Topic :: Software Development :: Libraries :: Python Modules
Requires-Dist: cupy-cuda11x (>=11.4.0,<12.0.0)
Requires-Dist: cuquantum (>=22.11.0,<23.0.0)
Requires-Dist: cuquantum-python (>=22.11.0,<23.0.0)
Requires-Dist: cutensornet-cu11 (>=2.0.0,<3.0.0)
Requires-Dist: numpy (>=1.23.5,<2.0.0)
